database_redis_local/__init__.py
database_redis_local/constants_src.py
database_redis_local/entity_constants.py
database_redis_local/generic_crud_redis.py
database_redis_local/point.py
database_redis_local/pycallgraph.py
database_redis_local/table_columns.py
database_redis_local/table_definition.py
database_redis_local/utils.py
database_redis_local-0.1.4.dist-info/METADATA
database_redis_local-0.1.4.dist-info/WHEEL
database_redis_local-0.1.4.dist-info/top_level.txt
database_redis_local-0.1.4.dist-info/RECORD
