Metadata-Version: 2.4
Name: database-redis-local
Version: 0.1.4
Summary: PyPI Package for Circles database-redis-local Python
Home-page: https://github.com/circles-zone/database-redis-local-python-package
Author: Circles
Author-email: info@circlez.ai
Classifier: Programming Language :: Python :: 3
Classifier: Operating System :: OS Independent
Requires-Dist: python-sdk-remote
Requires-Dist: logger-local
Requires-Dist: database-infrastructure-local>=0.1.4
Dynamic: author
Dynamic: author-email
Dynamic: classifier
Dynamic: description
Dynamic: description-content-type
Dynamic: home-page
Dynamic: requires-dist
Dynamic: summary
